{
  "global": {
    "purple": {
      "value": "#440099",
      "type": "color",
      "description": "primary purple"
    },
    "white": {
      "value": "#F6F8FA",
      "type": "color"
    },
    "button-lg": {
      "value": "100",
      "type": "borderRadius"
    },
    "shadow-lg": {
      "value": {
        "x": "0",
        "y": "0",
        "blur": "36",
        "spread": "0",
        "color": "rgba(68,0,153,0.4)",
        "type": "dropShadow"
      },
      "type": "boxShadow"
    },
    "p-12": {
      "value": "12px",
      "type": "spacing"
    },
    "p-16": {
      "value": "16px",
      "type": "spacing"
    }
  },
  "$themes": [],
  "$metadata": {
    "tokenSetOrder": [
      "global"
    ]
  }
}